libpecos.libs/libgomp-d22c30c5.so.1.0.0
pecos/__init__.py
pecos/_version.py
pecos/ann/__init__.py
pecos/ann/hnsw/__init__.py
pecos/ann/hnsw/model.py
pecos/ann/hnsw/predict.py
pecos/ann/hnsw/train.py
pecos/ann/pairwise/__init__.py
pecos/ann/pairwise/model.py
pecos/apps/__init__.py
pecos/apps/text2text/__init__.py
pecos/apps/text2text/evaluate.py
pecos/apps/text2text/model.py
pecos/apps/text2text/predict.py
pecos/apps/text2text/train.py
pecos/core/__init__.py
pecos/core/base.py
pecos/core/libpecos_float32.cpython-310-aarch64-linux-gnu.so
pecos/distributed/__init__.py
pecos/distributed/comm/__init__.py
pecos/distributed/comm/abs_dist_comm.py
pecos/distributed/comm/mpi_comm.py
pecos/distributed/diagnostic_tools/__init__.py
pecos/distributed/diagnostic_tools/deepspeed_comm.py
pecos/distributed/diagnostic_tools/mpi_comm.py
pecos/distributed/diagnostic_tools/test_util.py
pecos/distributed/xmc/__init__.py
pecos/distributed/xmc/base.py
pecos/distributed/xmc/xlinear/__init__.py
pecos/distributed/xmc/xlinear/model.py
pecos/distributed/xmc/xlinear/train.py
pecos/distributed/xmc/xtransformer/__init__.py
pecos/distributed/xmc/xtransformer/dist_trainer.py
pecos/distributed/xmc/xtransformer/encode.py
pecos/distributed/xmc/xtransformer/model.py
pecos/distributed/xmc/xtransformer/module.py
pecos/distributed/xmc/xtransformer/train.py
pecos/utils/__init__.py
pecos/utils/cli.py
pecos/utils/cluster_util.py
pecos/utils/logging_util.py
pecos/utils/mmap_hashmap_util.py
pecos/utils/mmap_valstore_util.py
pecos/utils/parallel_util.py
pecos/utils/profile_util.py
pecos/utils/smat_util.py
pecos/utils/torch_util.py
pecos/utils/featurization/__init__.py
pecos/utils/featurization/text/__init__.py
pecos/utils/featurization/text/preprocess.py
pecos/utils/featurization/text/vectorizers.py
pecos/utils/featurization/text/sentencepiece/__init__.py
pecos/utils/featurization/text/sentencepiece/model.py
libpecos-1.2.8.dist-info/LICENSE
libpecos-1.2.8.dist-info/METADATA
libpecos-1.2.8.dist-info/NOTICE
libpecos-1.2.8.dist-info/WHEEL
libpecos-1.2.8.dist-info/top_level.txt
libpecos-1.2.8.dist-info/RECORD
