Metadata-Version: 2.2
Name: libpecos
Version: 1.2.8
Summary: PECOS - Predictions for Enormous and Correlated Output Spaces
Home-page: https://github.com/amzn/pecos
Author: Amazon.com, Inc.
License: Apache 2.0
License-File: LICENSE
License-File: NOTICE
Requires-Dist: numpy<2.0.0,>=1.19.5; python_version >= "3.9"
Requires-Dist: scipy<1.14.0,>=1.4.1
Requires-Dist: scikit-learn>=0.24.1
Requires-Dist: torch>=2.0; python_version >= "3.9"
Requires-Dist: sentencepiece!=0.1.92,>=0.1.86
Requires-Dist: transformers>=4.31.0; python_version >= "3.9"
Requires-Dist: peft>=0.11.0; python_version >= "3.9"
Requires-Dist: datasets>=2.19.1; python_version >= "3.9"
Dynamic: author
Dynamic: description
Dynamic: description-content-type
Dynamic: home-page
Dynamic: license
Dynamic: requires-dist
Dynamic: summary
